{
  "name": "Cole Sprouse",
  "tags": [
    "actor",
    "american",
    "christian",
    "non-political",
    "non-religious",
    "white"
  ],
  "relatedPeople": [
    {
      "slug": "big-show",
      "name": "Big Show"
    },
    {
      "slug": "dylan-sprouse",
      "name": "Dylan Sprouse"
    },
    {
      "slug": "charles-bronson",
      "name": "Charles Bronson"
    },
    {
      "slug": "chris-colfer",
      "name": "Chris Colfer"
    }
  ],
  "lastUpdatedOn": "2012-12-28",
  "author": "Caitlin Frye",
  "content": [
    {
      "type": "paragraph",
      "id": 1
    },
    {
      "parentId": 1,
      "type": "text",
      "text": "Cole Sprouse was born in Arezzo, Italy and grew up in Long Beach, California."
    },
    {
      "type": "paragraph",
      "id": 2
    },
    {
      "parentId": 2,
      "type": "text",
      "text": "The information about Sprouse's religion is sparse. Most speculate that he and his twin brother, Dylan, are Christians.",
      "sourceTitle": "Dylan and Cole Sprouse :: Personal facts.",
      "sourceUrl": "http://sprouse.creatuforo.com/-temas31.html"
    },
    {
      "parentId": 2,
      "type": "text",
      "text": " That seems like a pretty good bet considering they are Americans. But there's not really anything else to go on."
    },
    {
      "type": "paragraph",
      "id": 3
    },
    {
      "parentId": 3,
      "type": "text",
      "text": "Cole has a Twitter account, but I couldn't find any mention of God, praying, or feeling blessed on there. His brother Dylan mentioned in an interview that he was looking for a nice Christian girl, but it seemed more like a joke than a sincere statement of longing.",
      "sourceTitle": "Cole and Dylan Sprouse on Ellen DeGeneres on October 2nd 2007.",
      "sourceUrl": "http://www.youtube.com/watch?v=aEK3ztQinMs"
    },
    {
      "type": "paragraph",
      "id": 4
    },
    {
      "parentId": 4,
      "type": "text",
      "text": "My guess is that even if Cole and his brother do consider themselves Christians, religion probably doesn't play too big a part in their lives–just like politics."
    },
    {
      "type": "paragraph",
      "id": 5
    },
    {
      "parentId": 5,
      "type": "text",
      "text": "Cole didn't even mention anything on his Twitter account over the 2012 presidential election, which was the first time he was old enough to vote. So I'm guessing he's either not into politics, or he doesn't want to deal with the inevitable backlash from his tween fans, no matter which side he chose. Regardless of whether he voted or for whom, apparently the Obama girls are fans of his.",
      "sourceTitle": "Sprouse Brothers Meet Obama Girls!!!",
      "sourceUrl": "http://www.sprouseland.com/2010/06/20/sprouse-brothers-meet-obama-girls/"
    },
    {
      "type": "paragraph",
      "id": 6
    },
    {
      "parentId": 6,
      "type": "text",
      "text": "I did find one tweet from Cole about teachers, which could potentially be a political statement:"
    },
    {
      "type": "quote",
      "id": 7
    },
    {
      "type": "paragraph",
      "id": 8,
      "parentId": 7
    },
    {
      "parentId": 8,
      "type": "text",
      "text": "This country will see improvement in the form of quality education. Respect your teachers, the job they do is one of love, not of money.",
      "sourceTitle": "TheOleKingCole: This country will see improvement …",
      "sourceUrl": "https://twitter.com/TheOleKingCole/status/280826697459322880"
    },
    {
      "type": "paragraph",
      "id": 9
    },
    {
      "parentId": 9,
      "type": "text",
      "text": "Maybe he's trying to say that improvements in our education system aren't going to come through testing, but on hiring good teachers. If Cole starts getting political, we're counting on you Sprouse Brothers fans to keep us updated in the comments!"
    }
  ],
  "wikipediaData": {
    "url": "https://en.wikipedia.org/wiki/Cole_Sprouse",
    "title": "Cole Sprouse",
    "image": {
      "name": "Cole_Sprouse_by_Gage_Skidmore.jpg",
      "info": {
        "canonicaltitle": "File:Cole Sprouse by Gage Skidmore.jpg",
        "thumburl": "https://upload.wikimedia.org/wikipedia/commons/thumb/2/2e/Cole_Sprouse_by_Gage_Skidmore.jpg/227px-Cole_Sprouse_by_Gage_Skidmore.jpg",
        "thumbwidth": 227,
        "thumbheight": 300,
        "url": "https://upload.wikimedia.org/wikipedia/commons/2/2e/Cole_Sprouse_by_Gage_Skidmore.jpg",
        "descriptionurl": "https://commons.wikimedia.org/wiki/File:Cole_Sprouse_by_Gage_Skidmore.jpg",
        "descriptionshorturl": "https://commons.wikimedia.org/w/index.php?curid=57703930",
        "extmetadata": {
          "DateTime": {
            "value": "2017-04-04 02:30:40",
            "source": "mediawiki-metadata",
            "hidden": ""
          },
          "ObjectName": {
            "value": "Cole Sprouse by Gage Skidmore",
            "source": "mediawiki-metadata",
            "hidden": ""
          },
          "CommonsMetadataExtension": {
            "value": 1.2,
            "source": "extension",
            "hidden": ""
          },
          "Categories": {
            "value": "Cole Sprouse|Photographs by Gage Skidmore|WonderCon 2017",
            "source": "commons-categories",
            "hidden": ""
          },
          "Assessments": {
            "value": "",
            "source": "commons-categories",
            "hidden": ""
          },
          "ImageDescription": {
            "value": "<a href=\"https://en.wikipedia.org/wiki/Cole_Sprouse\" class=\"extiw\" title=\"w:Cole Sprouse\">Cole Sprouse</a> speaking at the 2017 WonderCon in Anaheim, California.",
            "source": "commons-desc-page"
          },
          "DateTimeOriginal": {
            "value": "2017-03-31",
            "source": "commons-desc-page"
          },
          "Credit": {
            "value": "<span class=\"int-own-work\" lang=\"en\">Own work</span>",
            "source": "commons-desc-page",
            "hidden": ""
          },
          "Artist": {
            "value": "Gage Skidmore",
            "source": "commons-desc-page"
          },
          "Permission": {
            "value": "Must attribute to <b>Gage Skidmore</b> if used elsewhere, other than on Wikimedia and its projects.",
            "source": "commons-desc-page",
            "hidden": ""
          },
          "LicenseShortName": {
            "value": "CC BY-SA 3.0",
            "source": "commons-desc-page",
            "hidden": ""
          },
          "UsageTerms": {
            "value": "Creative Commons Attribution-Share Alike 3.0",
            "source": "commons-desc-page",
            "hidden": ""
          },
          "AttributionRequired": {
            "value": "true",
            "source": "commons-desc-page",
            "hidden": ""
          },
          "Attribution": {
            "value": "Gage Skidmore",
            "source": "commons-desc-page",
            "hidden": ""
          },
          "LicenseUrl": {
            "value": "https://creativecommons.org/licenses/by-sa/3.0",
            "source": "commons-desc-page",
            "hidden": ""
          },
          "Copyrighted": {
            "value": "True",
            "source": "commons-desc-page",
            "hidden": ""
          },
          "Restrictions": {
            "value": "",
            "source": "commons-desc-page",
            "hidden": ""
          },
          "License": {
            "value": "cc-by-sa-3.0",
            "source": "commons-templates",
            "hidden": ""
          }
        }
      }
    },
    "isDisambiguation": false
  }
}