{
  "name": "Demi Moore",
  "tags": [
    "actor",
    "democrat",
    "judaism",
    "kabbalah",
    "liberal",
    "producer",
    "white"
  ],
  "relatedPeople": [
    {
      "slug": "george-clooney",
      "name": "George Clooney"
    },
    {
      "slug": "tom-hanks",
      "name": "Tom Hanks"
    },
    {
      "slug": "charlize-theron",
      "name": "Charlize Theron"
    },
    {
      "slug": "steve-martin",
      "name": "Steve Martin"
    }
  ],
  "lastUpdatedOn": "2012-03-23",
  "religion": "Moore is a follower of Kabbalah, a mystical sect of Judaism.",
  "politicalViews": "She's a standard Hollywood liberal, Obama supporter and philanthropist.",
  "author": "Tom Kershaw",
  "content": [
    {
      "type": "paragraph",
      "id": 1
    },
    {
      "parentId": 1,
      "type": "text",
      "text": "Demi Moore was born in Roswell, New Mexico, the focus of many alien conspiracy theories. She didn't live there long, though, and has reported moving something like 40 times during her childhood.",
      "sourceTitle": "Biography for Demi Moore",
      "sourceUrl": "http://www.imdb.com/name/nm0000193/bio"
    },
    {
      "type": "paragraph",
      "id": 2
    },
    {
      "parentId": 2,
      "type": "text",
      "text": "Demi's parents were alcoholics and were not very religious.",
      "sourceTitle": "Demi Moore Biography.",
      "sourceUrl": "http://www.aceshowbiz.com/celebrity/demi_moore/biography.html"
    },
    {
      "parentId": 2,
      "type": "text",
      "text": " Possibly as a result, Moore has tried out many religions, now seeming to settle on Kabbalah, the Jewish sect made famous by various celebrities including Madonna and Britney Spears. Moore's daughter Scout once said:"
    },
    {
      "type": "quote",
      "id": 3
    },
    {
      "type": "paragraph",
      "id": 4,
      "parentId": 3
    },
    {
      "parentId": 4,
      "type": "text",
      "text": "She has always moved from religion to religion according to the stages in her life. Kabbalah is the one she has stuck with the most. I respect that she and [husband] Ashton are doing it.",
      "sourceTitle": "Demi Moore Poses with Daughters for Family Portrait",
      "sourceUrl": "http://www.people.com/people/article/0,,20182233,00.html"
    },
    {
      "type": "paragraph",
      "id": 5
    },
    {
      "parentId": 5,
      "type": "text",
      "text": "Demi herself has addressed the issue that she is not Jewish by heritage but feels a strong connection to the religion, even stronger than some genetic Jews. She said:"
    },
    {
      "type": "quote",
      "id": 6
    },
    {
      "type": "paragraph",
      "id": 7,
      "parentId": 6
    },
    {
      "parentId": 7,
      "type": "text",
      "text": "I didn't grow up Jewish, but I would say that I've been more exposed to the deeper meanings of particular rituals than any of my friends that did.",
      "sourceTitle": "Bar Mitzvah Nation",
      "sourceUrl": "http://web.archive.org/web/20060216205012/http://www.thejewishweek.com/top/editletcontent.php3?artid=3430"
    },
    {
      "type": "paragraph",
      "id": 8
    },
    {
      "parentId": 8,
      "type": "text",
      "text": "There must be something about Kabbalah that, like Scientology, attracts celebrities like a moth to a flame. Someone comment, please, and tell me why.\n"
    },
    {
      "type": "heading",
      "id": 9
    },
    {
      "parentId": 9,
      "type": "text",
      "text": "Standard Hollywood liberal"
    },
    {
      "type": "paragraph",
      "id": 10
    },
    {
      "parentId": 10,
      "type": "text",
      "text": "Moore is a liberal Democrat. She supported Obama's campaign in 2008 and is supporting his 2012 bid as well.",
      "sourceTitle": "Liberal Celebrities",
      "sourceUrl": "http://www.upi.com/News_Photos/Entertainment/Liberal-Celebrities/6010/8/"
    },
    {
      "parentId": 10,
      "type": "text",
      "text": "  She even went as far to say of Obama:"
    },
    {
      "type": "quote",
      "id": 11
    },
    {
      "type": "paragraph",
      "id": 12,
      "parentId": 11
    },
    {
      "parentId": 12,
      "type": "text",
      "text": "I pledge to be a servant of my president.",
      "sourceTitle": "1000 Points Of Creepiness: Demi Moore Claims I Pledge To Be A Servant To My President!.",
      "sourceUrl": "http://www.foundingbloggers.com/wordpress/2009/09/1000-points-of-creepiness-demi-moore-claims-i-pledge-to-be-a-servant-to-my-president/"
    },
    {
      "type": "paragraph",
      "id": 13
    },
    {
      "parentId": 13,
      "type": "text",
      "text": "That's a little creepy. And what if Obama does something crazy likes signs a law making it illegal to protest, or one that allows the military to detain U.S. citizens infinitely without charges, or assassinates U.S. citizens. Oh, wait.."
    },
    {
      "type": "paragraph",
      "id": 14
    },
    {
      "parentId": 14,
      "type": "text",
      "text": "Moore is committed to doing some good for society. She and Ashton Kutcher set up a foundation called DNA, the mission of which is to raise awareness and prevent child sex trafficking. A worthy cause indeed!",
      "sourceTitle": "Demiandashton",
      "sourceUrl": "http://demiandashton.org/"
    }
  ],
  "wikipediaData": {
    "url": "https://en.wikipedia.org/wiki/Demi_Moore",
    "title": "Demi Moore",
    "image": {
      "name": "Demi_Moore_2010_Time_100_Shankbone.jpg",
      "info": {
        "canonicaltitle": "File:Demi Moore 2010 Time 100 Shankbone.jpg",
        "thumburl": "https://upload.wikimedia.org/wikipedia/commons/thumb/e/e2/Demi_Moore_2010_Time_100_Shankbone.jpg/236px-Demi_Moore_2010_Time_100_Shankbone.jpg",
        "thumbwidth": 236,
        "thumbheight": 300,
        "url": "https://upload.wikimedia.org/wikipedia/commons/e/e2/Demi_Moore_2010_Time_100_Shankbone.jpg",
        "descriptionurl": "https://commons.wikimedia.org/wiki/File:Demi_Moore_2010_Time_100_Shankbone.jpg",
        "descriptionshorturl": "https://commons.wikimedia.org/w/index.php?curid=11705580",
        "extmetadata": {
          "DateTime": {
            "value": "2012-03-01 05:01:34",
            "source": "mediawiki-metadata",
            "hidden": ""
          },
          "ObjectName": {
            "value": "Demi Moore 2010 Time 100 Shankbone",
            "source": "mediawiki-metadata",
            "hidden": ""
          },
          "CommonsMetadataExtension": {
            "value": 1.2,
            "source": "extension",
            "hidden": ""
          },
          "Categories": {
            "value": "Demi Moore|Personality rights warning|Self-published work|Time 100 Gala",
            "source": "commons-categories",
            "hidden": ""
          },
          "Assessments": {
            "value": "",
            "source": "commons-categories",
            "hidden": ""
          },
          "ImageDescription": {
            "value": "<a href=\"https://en.wikipedia.org/wiki/Demi_Moore\" class=\"extiw\" title=\"w:Demi Moore\">Demi Moore</a> at the 2010 <a href=\"https://en.wikipedia.org/wiki/Time_100\" class=\"extiw\" title=\"w:Time 100\">Time 100</a>.",
            "source": "commons-desc-page"
          },
          "DateTimeOriginal": {
            "value": "2010-05-04",
            "source": "commons-desc-page"
          },
          "Credit": {
            "value": "Shankbone",
            "source": "commons-desc-page",
            "hidden": ""
          },
          "Artist": {
            "value": "<a rel=\"nofollow\" class=\"external text\" href=\"http://blog.shankbone.org\">David Shankbone</a>",
            "source": "commons-desc-page"
          },
          "LicenseShortName": {
            "value": "CC BY 3.0",
            "source": "commons-desc-page",
            "hidden": ""
          },
          "UsageTerms": {
            "value": "Creative Commons Attribution 3.0",
            "source": "commons-desc-page",
            "hidden": ""
          },
          "AttributionRequired": {
            "value": "true",
            "source": "commons-desc-page",
            "hidden": ""
          },
          "LicenseUrl": {
            "value": "http://creativecommons.org/licenses/by/3.0",
            "source": "commons-desc-page",
            "hidden": ""
          },
          "Copyrighted": {
            "value": "True",
            "source": "commons-desc-page",
            "hidden": ""
          },
          "Restrictions": {
            "value": "personality",
            "source": "commons-desc-page",
            "hidden": ""
          },
          "License": {
            "value": "cc-by-3.0",
            "source": "commons-templates",
            "hidden": ""
          }
        }
      }
    },
    "isDisambiguation": false
  }
}