{
  "name": "Doutzen Kroes",
  "tags": [
    "actress",
    "dutch",
    "liberal",
    "model",
    "non-religious",
    "white"
  ],
  "relatedPeople": [
    {
      "slug": "cameron-diaz",
      "name": "Cameron Diaz"
    },
    {
      "slug": "uma-thurman",
      "name": "Uma Thurman"
    },
    {
      "slug": "stacy-keibler",
      "name": "Stacy Keibler"
    },
    {
      "slug": "emily-browning",
      "name": "Emily Browning"
    }
  ],
  "lastUpdatedOn": "2013-03-13",
  "religion": "Doutzen Kroes is completely non-religious, except for the skimpy Santa suit she wore once.",
  "politicalViews": "She is a liberal Obama fan.",
  "author": "Caitlin Frye",
  "content": [
    {
      "type": "paragraph",
      "id": 1
    },
    {
      "parentId": 1,
      "type": "text",
      "text": "Doutzen Kroes was born in Eastermar, Friesland, the Netherlands."
    },
    {
      "type": "paragraph",
      "id": 2
    },
    {
      "parentId": 2,
      "type": "text",
      "text": "Over half the population of Kroes' home country, one of the most secular in the world, is non-religious,",
      "sourceTitle": "Religion in the Netherlands.",
      "sourceUrl": "http://en.wikipedia.org/wiki/Religion_in_the_Netherlands"
    },
    {
      "parentId": 2,
      "type": "text",
      "text": " and I'm afraid that our current subject is one of them. Mostly that's bad news because she doesn't give me hardly anything to write about."
    },
    {
      "type": "paragraph",
      "id": 3
    },
    {
      "parentId": 3,
      "type": "text",
      "text": "But let's see, the pseudo-Christian influence on her upbringing came out in 2012 when she  tweeted \"How was your Christmas?\" with a little Instagram "
    },
    {
      "parentId": 3,
      "type": "link",
      "text": "picture",
      "sourceUrl": "http://instagram.com/p/TtvI-pzVPj/"
    },
    {
      "parentId": 3,
      "type": "text",
      "text": " attached.",
      "sourceTitle": "Doutzen: How was your Christmas? …",
      "sourceUrl": "https://twitter.com/Doutzen/status/284046339183099905"
    },
    {
      "parentId": 3,
      "type": "text",
      "text": " So she celebrates Christmas, but apparently she does it wearing less fabric than it takes to make a baby sock.\n"
    },
    {
      "type": "heading",
      "id": 4
    },
    {
      "parentId": 4,
      "type": "text",
      "text": "Obama and the Liberal Worldview"
    },
    {
      "type": "paragraph",
      "id": 5
    },
    {
      "parentId": 5,
      "type": "text",
      "text": "Moving on, as you would expect from a Dutch woman, she is liberal when it comes to American politics. I couldn't find a thing about her political views in the country of her birth, but in the U.S. where she works and lives, she's an Obama fan. She wears Obama t-shirts out and about",
      "sourceTitle": "Doutzen Kroes and Barack Obama Progress T-Shirt.",
      "sourceUrl": "http://coolspotters.com/models/doutzen-kroes/and/clothing/barack-obama-progress-t-shirt#medium-246400"
    },
    {
      "parentId": 5,
      "type": "text",
      "text": " and she was all over Twitter supporting the president in 2012."
    },
    {
      "type": "paragraph",
      "id": 6
    },
    {
      "parentId": 6,
      "type": "text",
      "text": "She tweeted Obama quotes",
      "sourceTitle": "Doutzen Kroes tweets.",
      "sourceUrl": "http://tweetwood.com/Doutzen/tweet/217364285859430400"
    },
    {
      "parentId": 6,
      "type": "text",
      "text": " and her congratulations on election night.",
      "sourceTitle": "Twitter conversation between Doutzen Kroes and Barack Obama.",
      "sourceUrl": "http://tweetwood.com/conversation/Doutzen/BarackObama"
    },
    {
      "parentId": 6,
      "type": "text",
      "text": " But perhaps the best indication of her liberal worldview is her retweet of "
    },
    {
      "parentId": 6,
      "type": "link",
      "text": "this poster",
      "sourceUrl": "https://twitter.com/BarackObama/status/265290216716263424/photo/1"
    },
    {
      "parentId": 6,
      "type": "text",
      "text": " from Obama's campaign comparing Mitt Romney's quote that if people want to go to college, they should borrow money from their parents with Obama's:"
    },
    {
      "type": "quote",
      "id": 7
    },
    {
      "type": "paragraph",
      "id": 8,
      "parentId": 7
    },
    {
      "parentId": 8,
      "type": "text",
      "text": "A higher education can't be a luxury–it's an economic imperative that every American should be able to afford.",
      "sourceTitle": "Doutzen Kroes (Doutzen) on Twitter.",
      "sourceUrl": "https://twitter.com/Doutzen"
    },
    {
      "type": "paragraph",
      "id": 9
    },
    {
      "parentId": 9,
      "type": "text",
      "text": "That quote gets right to the meat of the distinction between liberal and conservative. Things like health care and education are things the government will either provide or help people afford–or they are the responsibility of the individual to provide for themselves, and government only gets in the way."
    },
    {
      "type": "paragraph",
      "id": 10
    },
    {
      "parentId": 10,
      "type": "text",
      "text": "Maybe this would be a good opportunity for you all to have a civil discussion about which is the better approach? Or maybe that's too heavy for Kroes' page. You decide amongst yourselves."
    }
  ],
  "wikipediaData": {
    "url": "https://en.wikipedia.org/wiki/Doutzen_Kroes",
    "title": "Doutzen Kroes",
    "image": {
      "name": "Doutzen_Kroes_Cannes_2015_2_(cropped).jpg",
      "info": {
        "canonicaltitle": "File:Doutzen Kroes Cannes 2015 2 (cropped).jpg",
        "thumburl": "https://upload.wikimedia.org/wikipedia/commons/thumb/8/8e/Doutzen_Kroes_Cannes_2015_2_%28cropped%29.jpg/264px-Doutzen_Kroes_Cannes_2015_2_%28cropped%29.jpg",
        "thumbwidth": 264,
        "thumbheight": 300,
        "url": "https://upload.wikimedia.org/wikipedia/commons/8/8e/Doutzen_Kroes_Cannes_2015_2_%28cropped%29.jpg",
        "descriptionurl": "https://commons.wikimedia.org/wiki/File:Doutzen_Kroes_Cannes_2015_2_(cropped).jpg",
        "descriptionshorturl": "https://commons.wikimedia.org/w/index.php?curid=58522990",
        "extmetadata": {
          "DateTime": {
            "value": "2017-05-05 18:46:51",
            "source": "mediawiki-metadata",
            "hidden": ""
          },
          "ObjectName": {
            "value": "Doutzen Kroes Cannes 2015 2 (cropped)",
            "source": "mediawiki-metadata",
            "hidden": ""
          },
          "CommonsMetadataExtension": {
            "value": 1.2,
            "source": "extension",
            "hidden": ""
          },
          "Categories": {
            "value": "2015 Cannes Film Festival|Doutzen Kroes in 2015|Extracted images|Images by Georges Biard|Items with OTRS permission confirmed|Personality rights warning|Self-published work",
            "source": "commons-categories",
            "hidden": ""
          },
          "Assessments": {
            "value": "",
            "source": "commons-categories",
            "hidden": ""
          },
          "ImageDescription": {
            "value": "Doutzen Kroes au festival de Cannes",
            "source": "commons-desc-page"
          },
          "DateTimeOriginal": {
            "value": "2015-05",
            "source": "commons-desc-page"
          },
          "Credit": {
            "value": "<span class=\"int-own-work\" lang=\"en\">Own work</span>",
            "source": "commons-desc-page",
            "hidden": ""
          },
          "Artist": {
            "value": "Georges Biard",
            "source": "commons-desc-page"
          },
          "Permission": {
            "value": "<table class=\"messagebox layouttemplate\" style=\"margin:0.3em 0;width:100%;direction:ltr\"><tr>\n<td width=\"70\">\n<img alt=\"OTRS Wikimedia\" src=\"https://upload.wikimedia.org/wikipedia/commons/thumb/1/1d/OTRS_Wikimedia.svg/70px-OTRS_Wikimedia.svg.png\" title=\"OTRS Wikimedia\" width=\"70\" height=\"38\" srcset=\"https://upload.wikimedia.org/wikipedia/commons/thumb/1/1d/OTRS_Wikimedia.svg/105px-OTRS_Wikimedia.svg.png 1.5x, https://upload.wikimedia.org/wikipedia/commons/thumb/1/1d/OTRS_Wikimedia.svg/140px-OTRS_Wikimedia.svg.png 2x\" data-file-width=\"120\" data-file-height=\"65\"><p><span class=\"layouttemplateargs\" style=\"display:none;speak:none;\" title=\"template=PermissionOTRS 1%3Dhttps%3A%2F%2Fticket.wikimedia.org%2Fotrs%2Findex.pl%3FAction%3DAgentTicketZoom%26TicketNumber%3D2012010510013998 2%3D2012010510013998\"> </span></p>\n</td>\n<td>\n<span lang=\"en\" class=\"description en\">This work is <a href=\"http://freedomdefined.org/Definition\" class=\"extiw\" title=\"freedomdefined:Definition\">free</a> and may be used by anyone for any purpose. If you wish to <b><a href=\"//commons.wikimedia.org/wiki/Commons:Reusing_content_outside_Wikimedia\" title=\"Commons:Reusing content outside Wikimedia\">use this content</a></b>, you do not need to request permission as long as you follow any licensing requirements mentioned on this page.</span>\n<p><span lang=\"en\" class=\"description en\">Wikimedia has received an e-mail confirming that the copyright holder has approved publication under the terms mentioned on this page. This correspondence has been <b><span style=\"background:transparent;color:#0f7f1f;\" title=\"transparent\">reviewed</span></b> by an <a href=\"//commons.wikimedia.org/wiki/Category:Commons_OTRS_volunteers\" title=\"Category:Commons OTRS volunteers\">OTRS member</a> and stored in our <a href=\"//commons.wikimedia.org/wiki/Commons:OTRS\" title=\"Commons:OTRS\">permission archive</a>. The correspondence is available to trusted volunteers <span class=\"plainlinksneverexpand\">as <b><a class=\"external text\" href=\"https://ticket.wikimedia.org/otrs/index.pl?Action=AgentTicketZoom&amp;TicketNumber=2012010510013998\">ticket #2012010510013998</a></b></span>.</span></p>\n<p><small>If you have questions about the archived correspondence, please use the <a href=\"//commons.wikimedia.org/wiki/Commons:OTRS/Noticeboard\" title=\"Commons:OTRS/Noticeboard\">OTRS noticeboard</a>.</small><br><small>Ticket link: <a class=\"external free\" href=\"https://ticket.wikimedia.org/otrs/index.pl?Action=AgentTicketZoom&amp;TicketNumber=2012010510013998\">https://ticket.wikimedia.org/otrs/index.pl?Action=AgentTicketZoom&amp;TicketNumber=2012010510013998</a></small> <span id=\"field-otrs\" title=\"https://ticket.wikimedia.org/otrs/index.pl?Action=AgentTicketZoom&amp;TicketNumber=2012010510013998\"></span></p>\n</td>\n</tr></table>\n<span class=\"autoconfonly\" id=\"otrstemplatewr\" style=\"display:none;\"></span>",
            "source": "commons-desc-page",
            "hidden": ""
          },
          "LicenseShortName": {
            "value": "CC BY-SA 3.0",
            "source": "commons-desc-page",
            "hidden": ""
          },
          "UsageTerms": {
            "value": "Creative Commons Attribution-Share Alike 3.0",
            "source": "commons-desc-page",
            "hidden": ""
          },
          "AttributionRequired": {
            "value": "true",
            "source": "commons-desc-page",
            "hidden": ""
          },
          "Attribution": {
            "value": "Georges Biard",
            "source": "commons-desc-page",
            "hidden": ""
          },
          "LicenseUrl": {
            "value": "https://creativecommons.org/licenses/by-sa/3.0",
            "source": "commons-desc-page",
            "hidden": ""
          },
          "Copyrighted": {
            "value": "True",
            "source": "commons-desc-page",
            "hidden": ""
          },
          "Restrictions": {
            "value": "personality",
            "source": "commons-desc-page",
            "hidden": ""
          },
          "License": {
            "value": "cc-by-sa-3.0",
            "source": "commons-templates",
            "hidden": ""
          }
        }
      }
    },
    "isDisambiguation": false
  }
}