{
  "name": "Ian Somerhalder",
  "tags": [
    "actor",
    "american",
    "catholic",
    "democrat",
    "liberal",
    "model",
    "white"
  ],
  "relatedPeople": [
    {
      "slug": "zooey-deschanel",
      "name": "Zooey Deschanel"
    },
    {
      "slug": "darren-criss",
      "name": "Darren Criss"
    },
    {
      "slug": "stacy-keibler",
      "name": "Stacy Keibler"
    },
    {
      "slug": "justin-long",
      "name": "Justin Long"
    }
  ],
  "lastUpdatedOn": "2012-08-20",
  "religion": "Somerhalder was raised a strict Catholic, but it's unclear what his current level of devotion is.",
  "politicalViews": "Somerhalder is a liberal Democrat whose political life revolves around environmental issues.",
  "author": "Tom Kershaw",
  "content": [
    {
      "type": "paragraph",
      "id": 1
    },
    {
      "parentId": 1,
      "type": "text",
      "text": "Ian Somerhalder was born and raised in Convington, Louisiana, just outside of New Orleans."
    },
    {
      "type": "paragraph",
      "id": 2
    },
    {
      "parentId": 2,
      "type": "text",
      "text": "Somerhalder was raised a Catholic, he attended Catholic school, and describes his mother and her influence on his childhood as \"very spiritual.\"",
      "sourceTitle": "Ian Somerhalder – Biography",
      "sourceUrl": "http://www.imdb.com/name/nm0813812/bio"
    },
    {
      "type": "paragraph",
      "id": 3
    },
    {
      "parentId": 3,
      "type": "text",
      "text": "Other than that, he gives very little indication of being spiritual himself, or that much in to Catholicism. In fact, one might wonder given that he has made his fortune as perhaps the most anti-Catholic of all of the Halloween costumes–a vampire."
    },
    {
      "type": "paragraph",
      "id": 4
    },
    {
      "parentId": 4,
      "type": "text",
      "text": "Beyond that, Ian takes a rather natural science/empirical view of the ontological \"what is it to be human\" question, saying:"
    },
    {
      "type": "quote",
      "id": 5
    },
    {
      "type": "paragraph",
      "id": 6,
      "parentId": 5
    },
    {
      "parentId": 6,
      "type": "text",
      "text": "We're made up of energy, so who's to say you can't transmit through electrical means?",
      "sourceTitle": "Life After Lost: Ian Somerhalder.",
      "sourceUrl": "http://www.people.com/people/archive/article/0,,20060073,00.html"
    },
    {
      "type": "paragraph",
      "id": 7
    },
    {
      "parentId": 7,
      "type": "text",
      "text": "To me, that view seems to conflict with the Judeo-Christian conception of humans as souls with a physical shell. So, I guess, he's not hardcore Catholic or anything, at least to the point of ignoring scientific principles, even if they are a bit ridiculously sci-fi."
    },
    {
      "type": "heading",
      "id": 8
    },
    {
      "parentId": 8,
      "type": "text",
      "text": "Religious/political transference"
    },
    {
      "type": "paragraph",
      "id": 9
    },
    {
      "parentId": 9,
      "type": "text",
      "text": "Check out Michael Crichton's take on environmentalism. He says it's a religion. If he's right, Somerhalder is certainly a devout follower. His biggest concern is the environment. He says things like:"
    },
    {
      "type": "quote",
      "id": 10
    },
    {
      "type": "paragraph",
      "id": 11,
      "parentId": 10
    },
    {
      "parentId": 11,
      "type": "text",
      "text": "What we're doing to the planet is inexcusable.",
      "sourceTitle": "Ian Somerhalder Quotes",
      "sourceUrl": "http://www.brainyquote.com/quotes/authors/i/ian_somerhalder_3.html"
    },
    {
      "type": "paragraph",
      "id": 12
    },
    {
      "parentId": 12,
      "type": "text",
      "text": "Somerhalder seems to base all of his political decisions around environmental issues, and despite explicitly saying he's not the kind of actor that wants to push his political agenda,",
      "sourceTitle": "Ian Somerhalder Quotes",
      "sourceUrl": "http://www.brainyquote.com/quotes/authors/i/ian_somerhalder_2.html"
    },
    {
      "type": "text",
      "text": "he'll tweet things like this:",
      "parentId": 12
    },
    {
      "type": "quote",
      "id": 13
    },
    {
      "type": "paragraph",
      "id": 14,
      "parentId": 13
    },
    {
      "parentId": 14,
      "type": "text",
      "text": "Just read a scary report: Romney was ahead of Obama by 2%. Whatever u believe, trust me this is extremely bad news for our environment & country.",
      "sourceTitle": "Ian Somerhalder unleashes \"plague\" of tweets about Obama and global warming",
      "sourceUrl": "http://twitchy.com/2012/07/28/ian-somerhalder-unleashes-plague-of-tweets-about-obama-and-global-warming/"
    },
    {
      "type": "paragraph",
      "id": 15
    },
    {
      "parentId": 15,
      "type": "text",
      "text": "In fact, Somerhalder's twitter feed is a constant barrage of environmental platitudes and \"green living\" suggestions, much to the chagrin of some of his followers. Plus, he's on President Obama's team of celebrity green energy advisers.",
      "sourceTitle": "Ian Somerhalder unleashes \"plague\" of tweets about Obama and global warming",
      "sourceUrl": "http://twitchy.com/2012/07/28/ian-somerhalder-unleashes-plague-of-tweets-about-obama-and-global-warming/"
    },
    {
      "type": "text",
      "text": "I'm sure that's just about the most powerful think-tank in all of Washington.",
      "parentId": 15
    },
    {
      "type": "paragraph",
      "id": 16
    },
    {
      "parentId": 16,
      "type": "text",
      "text": "Actually, that's kind of scary."
    },
    {
      "type": "paragraph",
      "id": 17
    },
    {
      "parentId": 17,
      "type": "text",
      "text": "It almost goes without saying, then, that Somerhalder is a Democrat and a giant Obama supporter. He's been successfully snared by the Obama propaganda machine. The president had him starstruck at a meeting",
      "sourceTitle": "Ian Somerhalder, Jared Leto, Other Celebs Starstruck At Meeting With President Obama",
      "sourceUrl": "http://www.vh1.com/celebrity/2012-06-08/president-obama-has-private-breakfast-meeting-for-young-america-effort-with-25-hollywood-stars/"
    },
    {
      "type": "text",
      "text": "and ever since, Somerhalder's been doing free campaign work, all in the name of the environment.",
      "parentId": 17,
      "sourceTitle": "Ian Somerhalder unleashes \"plague\" of tweets about Obama and global warming",
      "sourceUrl": "http://twitchy.com/2012/07/28/ian-somerhalder-unleashes-plague-of-tweets-about-obama-and-global-warming/"
    }
  ],
  "wikipediaData": {
    "url": "https://en.wikipedia.org/wiki/Ian_Somerhalder",
    "title": "Ian Somerhalder",
    "image": {
      "name": "Ian_Somerhalder_June_2013.jpg",
      "info": {
        "canonicaltitle": "File:Ian Somerhalder June 2013.jpg",
        "thumburl": "https://upload.wikimedia.org/wikipedia/commons/thumb/c/c9/Ian_Somerhalder_June_2013.jpg/215px-Ian_Somerhalder_June_2013.jpg",
        "thumbwidth": 215,
        "thumbheight": 300,
        "url": "https://upload.wikimedia.org/wikipedia/commons/c/c9/Ian_Somerhalder_June_2013.jpg",
        "descriptionurl": "https://commons.wikimedia.org/wiki/File:Ian_Somerhalder_June_2013.jpg",
        "descriptionshorturl": "https://commons.wikimedia.org/w/index.php?curid=51256748",
        "extmetadata": {
          "DateTime": {
            "value": "2016-09-09 04:30:22",
            "source": "mediawiki-metadata",
            "hidden": ""
          },
          "ObjectName": {
            "value": "Ian Somerhalder June 2013",
            "source": "mediawiki-metadata",
            "hidden": ""
          },
          "CommonsMetadataExtension": {
            "value": 1.2,
            "source": "extension",
            "hidden": ""
          },
          "Categories": {
            "value": "Flickr images reviewed by trusted users|Ian Somerhalder|Ian Somerhalder in groups|Taken with Canon EOS 550D",
            "source": "commons-categories",
            "hidden": ""
          },
          "Assessments": {
            "value": "",
            "source": "commons-categories",
            "hidden": ""
          },
          "ImageDescription": {
            "value": "Cropped out of a larger photo containing Candice Accola, Matt Davis, Ian Somerhalder, Michael Trevino &amp; Jenna Ushkowitz",
            "source": "commons-desc-page"
          },
          "DateTimeOriginal": {
            "value": "2013-06-16 17:48:01",
            "source": "commons-desc-page"
          },
          "Credit": {
            "value": "Cropped from Flickr version: <a rel=\"nofollow\" class=\"external autonumber\" href=\"https://www.flickr.com/photos/vagueonthehow/9119400586\">[1]</a>",
            "source": "commons-desc-page",
            "hidden": ""
          },
          "Artist": {
            "value": "<a rel=\"nofollow\" class=\"external text\" href=\"https://www.flickr.com/photos/vagueonthehow/\">Rach</a>",
            "source": "commons-desc-page"
          },
          "LicenseShortName": {
            "value": "CC BY 2.0",
            "source": "commons-desc-page",
            "hidden": ""
          },
          "UsageTerms": {
            "value": "Creative Commons Attribution 2.0",
            "source": "commons-desc-page",
            "hidden": ""
          },
          "AttributionRequired": {
            "value": "true",
            "source": "commons-desc-page",
            "hidden": ""
          },
          "LicenseUrl": {
            "value": "http://creativecommons.org/licenses/by/2.0",
            "source": "commons-desc-page",
            "hidden": ""
          },
          "Copyrighted": {
            "value": "True",
            "source": "commons-desc-page",
            "hidden": ""
          },
          "Restrictions": {
            "value": "",
            "source": "commons-desc-page",
            "hidden": ""
          },
          "License": {
            "value": "cc-by-2.0",
            "source": "commons-templates",
            "hidden": ""
          }
        }
      }
    },
    "isDisambiguation": false
  }
}