{
  "name": "Jack White",
  "tags": [
    "actor",
    "american",
    "catholic",
    "musician",
    "non-political",
    "producer",
    "singer",
    "white"
  ],
  "relatedPeople": [
    {
      "slug": "joe-pesci",
      "name": "Joe Pesci"
    },
    {
      "slug": "patrick-swayze",
      "name": "Patrick Swayze"
    },
    {
      "slug": "jerry-lewis",
      "name": "Jerry Lewis"
    },
    {
      "slug": "matt-leblanc",
      "name": "Matt LeBlanc"
    }
  ],
  "lastUpdatedOn": "2012-09-29",
  "religion": "White was raised a devout Catholic. He still identifies with Catholicism but potentially finds spiritual fulfillment in any religion.",
  "politicalViews": "White seems a bit liberal--and has expressed certain political frustrations. But overall, he wants to keep his political beliefs to himself.",
  "author": "Tom Kershaw",
  "content": [
    {
      "type": "paragraph",
      "id": 1
    },
    {
      "parentId": 1,
      "type": "text",
      "text": "Jack White, born John Anthony Gillis, was born and raised in Detroit, Michigan."
    },
    {
      "type": "paragraph",
      "id": 2
    },
    {
      "parentId": 2,
      "type": "text",
      "text": "White was raised in a classic Catholic family, the youngest of ten children. And it must have had a major influence on the young singer. As a teenager, White was seriously considering becoming a man of the cloth–but he went another direction, saying:"
    },
    {
      "type": "quote",
      "id": 3
    },
    {
      "type": "paragraph",
      "id": 4,
      "parentId": 3
    },
    {
      "parentId": 4,
      "type": "text",
      "text": "I'd got accepted to the seminary in Wisconsin, and I was gonna become a priest, but the last second I thought, 'I'll just go to public school.' I had just gotten a new amplifier in my bedroom, and I didn't think I was allowed to take it with me.",
      "sourceTitle": "Choosing Music Over Religion",
      "sourceUrl": "http://www.cbsnews.com/2100-500164_162-672415.html"
    },
    {
      "type": "paragraph",
      "id": 5
    },
    {
      "parentId": 5,
      "type": "text",
      "text": "And a rock 'n roll legend was born."
    },
    {
      "type": "paragraph",
      "id": 6
    },
    {
      "parentId": 6,
      "type": "text",
      "text": "But that doesn't mean White doesn't enjoy a good Catholic showdown every now and then. He and fellow lifelong Catholic, Stephen Colbert challenged each other to a test of Catholic knowledge once–and"
    },
    {
      "parentId": 6,
      "type": "link",
      "text": "filmed it",
      "sourceUrl": "http://www.huffingtonpost.com/2011/06/24/jack-white-stephen-colbert_n_884052.html"
    },
    {
      "type": "text",
      "text": "with hilarious results. The funniest part? Neither of them got very many answers right.",
      "parentId": 6
    },
    {
      "type": "paragraph",
      "id": 7
    },
    {
      "parentId": 7,
      "type": "text",
      "text": "Nowadays, White is still a very spiritual person and claims Catholicism–but only because its in his background. It might be anything for White:"
    },
    {
      "type": "quote",
      "id": 8
    },
    {
      "type": "paragraph",
      "id": 9,
      "parentId": 8
    },
    {
      "parentId": 9,
      "type": "text",
      "text": "I feel strongly connected to God. My roots are Catholic by default. I can take elements from Buddhism or other religions and see the similarities and differences in those, and learn from those, but at the end of the day, I don't care as much about man's interpretation of religion. What I care about is what God tells me directly.",
      "sourceTitle": "Jack White's Many Sides",
      "sourceUrl": "http://www.relevantmagazine.com/culture/music/features/20878-jack-whites-many-sides"
    },
    {
      "type": "heading",
      "id": 10
    },
    {
      "type": "heading",
      "id": 11
    },
    {
      "parentId": 11,
      "type": "text",
      "text": "No politics is the best politics"
    },
    {
      "type": "paragraph",
      "id": 12
    },
    {
      "parentId": 12,
      "type": "text",
      "text": "White"
    },
    {
      "parentId": 12,
      "type": "emphasis",
      "text": "used"
    },
    {
      "type": "text",
      "text": "to be into politics when he was a teenager,",
      "parentId": 12,
      "sourceTitle": "The White Stripes",
      "sourceUrl": "http://www.whitestripes.net/faq.php#politics"
    },
    {
      "type": "text",
      "text": "then he decided it just wasn't appropriate for an artist. He said, making a strong point:",
      "parentId": 12
    },
    {
      "type": "quote",
      "id": 13
    },
    {
      "type": "paragraph",
      "id": 14,
      "parentId": 13
    },
    {
      "parentId": 14,
      "type": "text",
      "text": "I have never thought that rock music can have a direct influence on anything in relation to questions about war and peace or famine. Perhaps it doesn't any longer make a difference what other things they are concerned with. If the Beatles could not get us all to love one another, then how would the White Stripes be capable to do it?",
      "sourceTitle": "The White Stripes",
      "sourceUrl": "http://www.whitestripes.net/faq.php#politics"
    },
    {
      "type": "paragraph",
      "id": 15
    },
    {
      "parentId": 15,
      "type": "text",
      "text": "White still gets a little upset about the current state of things. He's made comments regarding what he (and many others) see as the pointlessness of modern political parties and the non-choices they offer their public. He said:"
    },
    {
      "type": "quote",
      "id": 16
    },
    {
      "type": "paragraph",
      "id": 17,
      "parentId": 16
    },
    {
      "parentId": 17,
      "type": "text",
      "text": "When you belong to a political party, it doesn't matter if it's a monkey or Einstein who's the one running, you vote for him because he's a part of that party.",
      "sourceTitle": "The White Stripes",
      "sourceUrl": "http://www.whitestripes.net/faq.php#politics"
    },
    {
      "type": "paragraph",
      "id": 18
    },
    {
      "parentId": 18,
      "type": "text",
      "text": "White's probably a bit liberal, though, despite his unwillingness to express any explicit political views. He has played benefit concerts for environmental NGO Greenpeace.",
      "sourceTitle": "Global Stars Launch Campaign To Save The Arctic",
      "sourceUrl": "http://www.greenpeace.org/usa/en/media-center/news-releases/GLOBAL-STARS-LAUNCH-CAMPAIGN-TO-SAVE-THE-ARCTIC/"
    }
  ],
  "wikipediaData": {
    "url": "https://en.wikipedia.org/wiki/Jack_White",
    "title": "Jack White",
    "image": {
      "name": "Jack_White_Ottawa.jpg",
      "info": {
        "canonicaltitle": "File:Jack White Ottawa.jpg",
        "thumburl": "https://upload.wikimedia.org/wikipedia/commons/thumb/1/11/Jack_White_Ottawa.jpg/214px-Jack_White_Ottawa.jpg",
        "thumbwidth": 214,
        "thumbheight": 300,
        "url": "https://upload.wikimedia.org/wikipedia/commons/1/11/Jack_White_Ottawa.jpg",
        "descriptionurl": "https://commons.wikimedia.org/wiki/File:Jack_White_Ottawa.jpg",
        "descriptionshorturl": "https://commons.wikimedia.org/w/index.php?curid=8032269",
        "extmetadata": {
          "DateTime": {
            "value": "2010-12-06 21:20:37",
            "source": "mediawiki-metadata",
            "hidden": ""
          },
          "ObjectName": {
            "value": "Jack White Ottawa",
            "source": "mediawiki-metadata",
            "hidden": ""
          },
          "CommonsMetadataExtension": {
            "value": 1.2,
            "source": "extension",
            "hidden": ""
          },
          "Categories": {
            "value": "Files from Scott Penner Flickr stream|Flickr images reviewed by trusted users|Jack White",
            "source": "commons-categories",
            "hidden": ""
          },
          "Assessments": {
            "value": "",
            "source": "commons-categories",
            "hidden": ""
          },
          "ImageDescription": {
            "value": "<p>Cicso Ottawa Bluesfest 2009 Sunday July 19 2009 Rogers Stage</p>\n<p>Band members Alison Mosshart; lead vocals, guitar, percussion Jack White; drums, vocals, guitar Dean Fertita; guitar, organ, piano, synthesizer, bass, backing vocals Jack Lawrence; bass, guitar, drums, backing vocals</p>",
            "source": "commons-desc-page"
          },
          "DateTimeOriginal": {
            "value": "2009-07-19 20:42",
            "source": "commons-desc-page"
          },
          "Credit": {
            "value": "<a rel=\"nofollow\" class=\"external text\" href=\"http://www.flickr.com/photos/31648498@N00/3916144548/\">The Dead Weather @ Ottawa Bluesfest2009</a>",
            "source": "commons-desc-page",
            "hidden": ""
          },
          "Artist": {
            "value": "<a rel=\"nofollow\" class=\"external text\" href=\"http://www.flickr.com/people/31648498@N00\">Scott Penner</a> from Ottawa, Canada",
            "source": "commons-desc-page"
          },
          "LicenseShortName": {
            "value": "CC BY-SA 2.0",
            "source": "commons-desc-page",
            "hidden": ""
          },
          "UsageTerms": {
            "value": "Creative Commons Attribution-Share Alike 2.0",
            "source": "commons-desc-page",
            "hidden": ""
          },
          "AttributionRequired": {
            "value": "true",
            "source": "commons-desc-page",
            "hidden": ""
          },
          "LicenseUrl": {
            "value": "https://creativecommons.org/licenses/by-sa/2.0",
            "source": "commons-desc-page",
            "hidden": ""
          },
          "Copyrighted": {
            "value": "True",
            "source": "commons-desc-page",
            "hidden": ""
          },
          "Restrictions": {
            "value": "",
            "source": "commons-desc-page",
            "hidden": ""
          },
          "License": {
            "value": "cc-by-sa-2.0",
            "source": "commons-templates",
            "hidden": ""
          }
        }
      }
    },
    "isDisambiguation": false
  }
}