{
  "name": "James Roday",
  "relatedPeople": [
    {
      "slug": "louis-ck",
      "name": "Louis C.K."
    },
    {
      "slug": "sylvester-stallone",
      "name": "Sylvester Stallone"
    },
    {
      "slug": "seth-macfarlane",
      "name": "Seth MacFarlane"
    },
    {
      "slug": "stephen-fry",
      "name": "Stephen Fry"
    }
  ],
  "tags": [
    "actor",
    "director",
    "hispanic",
    "screenwriter",
    "white"
  ],
  "wikipediaData": {
    "url": "https://en.wikipedia.org/wiki/James_Roday",
    "title": "James Roday",
    "image": {
      "name": "James_Roday_by_Gage_Skidmore.jpg",
      "info": {
        "canonicaltitle": "File:James Roday by Gage Skidmore.jpg",
        "thumburl": "https://upload.wikimedia.org/wikipedia/commons/thumb/3/32/James_Roday_by_Gage_Skidmore.jpg/255px-James_Roday_by_Gage_Skidmore.jpg",
        "thumbwidth": 255,
        "thumbheight": 300,
        "url": "https://upload.wikimedia.org/wikipedia/commons/3/32/James_Roday_by_Gage_Skidmore.jpg",
        "descriptionurl": "https://commons.wikimedia.org/wiki/File:James_Roday_by_Gage_Skidmore.jpg",
        "descriptionshorturl": "https://commons.wikimedia.org/w/index.php?curid=27437253",
        "extmetadata": {
          "DateTime": {
            "value": "2013-07-26 04:00:13",
            "source": "mediawiki-metadata",
            "hidden": ""
          },
          "ObjectName": {
            "value": "James Roday by Gage Skidmore",
            "source": "mediawiki-metadata",
            "hidden": ""
          },
          "CommonsMetadataExtension": {
            "value": 1.2,
            "source": "extension",
            "hidden": ""
          },
          "Categories": {
            "value": "James Roday|Photographs by Gage Skidmore|Psych panel at the 2013 Comic-Con International",
            "source": "commons-categories",
            "hidden": ""
          },
          "Assessments": {
            "value": "",
            "source": "commons-categories",
            "hidden": ""
          },
          "ImageDescription": {
            "value": "<a href=\"https://en.wikipedia.org/wiki/James_Roday\" class=\"extiw\" title=\"w:James Roday\">James Roday</a> at the 2013 San Diego Comic Con International in San Diego, California.",
            "source": "commons-desc-page"
          },
          "DateTimeOriginal": {
            "value": "2013-07-18",
            "source": "commons-desc-page"
          },
          "Credit": {
            "value": "<span class=\"int-own-work\" lang=\"en\">Own work</span>",
            "source": "commons-desc-page",
            "hidden": ""
          },
          "Artist": {
            "value": "Gage Skidmore",
            "source": "commons-desc-page"
          },
          "Permission": {
            "value": "Must attribute to <b>Gage Skidmore</b> if used elsewhere, other than on Wikimedia and its projects.",
            "source": "commons-desc-page",
            "hidden": ""
          },
          "LicenseShortName": {
            "value": "CC BY-SA 3.0",
            "source": "commons-desc-page",
            "hidden": ""
          },
          "UsageTerms": {
            "value": "Creative Commons Attribution-Share Alike 3.0",
            "source": "commons-desc-page",
            "hidden": ""
          },
          "AttributionRequired": {
            "value": "true",
            "source": "commons-desc-page",
            "hidden": ""
          },
          "Attribution": {
            "value": "Gage Skidmore",
            "source": "commons-desc-page",
            "hidden": ""
          },
          "LicenseUrl": {
            "value": "https://creativecommons.org/licenses/by-sa/3.0",
            "source": "commons-desc-page",
            "hidden": ""
          },
          "Copyrighted": {
            "value": "True",
            "source": "commons-desc-page",
            "hidden": ""
          },
          "Restrictions": {
            "value": "",
            "source": "commons-desc-page",
            "hidden": ""
          },
          "License": {
            "value": "cc-by-sa-3.0",
            "source": "commons-templates",
            "hidden": ""
          }
        }
      }
    },
    "isDisambiguation": false
  }
}