{
  "name": "Peter Jackson",
  "relatedPeople": [
    {
      "slug": "steve-carell",
      "name": "Steve Carell"
    },
    {
      "slug": "nicolas-cage",
      "name": "Nicolas Cage"
    },
    {
      "slug": "seth-macfarlane",
      "name": "Seth MacFarlane"
    },
    {
      "slug": "ben-stiller",
      "name": "Ben Stiller"
    }
  ],
  "tags": [
    "director",
    "new-zealand",
    "producer",
    "white"
  ],
  "wikipediaData": {
    "url": "https://en.wikipedia.org/wiki/Peter_Jackson",
    "title": "Peter Jackson",
    "thumbnail": {
      "source": "https://upload.wikimedia.org/wikipedia/commons/thumb/4/4a/Peter_Jackson_SDCC_2014.jpg/212px-Peter_Jackson_SDCC_2014.jpg",
      "width": 212,
      "height": 300
    },
    "isDisambiguation": false
  }
}