{
  "name": "Tamer Hosny",
  "tags": [
    "actor",
    "composer",
    "director",
    "egyptian",
    "musician",
    "muslim",
    "non-political",
    "religious",
    "singer"
  ],
  "relatedPeople": [
    {
      "slug": "jason-derulo",
      "name": "Jason Derülo"
    },
    {
      "slug": "joe-jonas",
      "name": "Joe Jonas"
    },
    {
      "slug": "david-archuleta",
      "name": "David Archuleta"
    },
    {
      "slug": "amitabh-bachchan",
      "name": "Amitabh Bachchan"
    }
  ],
  "lastUpdatedOn": "2013-01-18",
  "religion": "Hosny is a devout Muslim.",
  "politicalViews": "Although he supported the Mubarak regime for about one minute, he later sided with the revolutionaries in Egypt. Now he prefers to stay non-political.",
  "author": "Caitlin Frye",
  "content": [
    {
      "type": "paragraph",
      "id": 1
    },
    {
      "parentId": 1,
      "type": "text",
      "text": "Tamer Hosny was born and raised in Cairo, Egypt."
    },
    {
      "type": "paragraph",
      "id": 2
    },
    {
      "parentId": 2,
      "type": "text",
      "text": "Considering I don't speak Arabic, and Hosny doesn't appear to speak a whole lot of English, I'll do my best on Hosny's worldview."
    },
    {
      "type": "paragraph",
      "id": 3
    },
    {
      "parentId": 3,
      "type": "text",
      "text": "Hosny is a devout Muslim. His music is laced with religious themes–and his album "
    },
    {
      "parentId": 3,
      "type": "emphasis",
      "text": "ElGana Fi Byotna"
    },
    {
      "parentId": 3,
      "type": "text",
      "text": " is a collection of Muslim- and Ramadan-themed songs.",
      "sourceTitle": "ElGana Fi Byotna.",
      "sourceUrl": "http://en.wikipedia.org/wiki/ElGana_Fi_Byotna"
    },
    {
      "parentId": 3,
      "type": "text",
      "text": " I found many songs with \"Allah\" in the name,",
      "sourceTitle": "Tamer Hosny lyrics : 116 songs translated 147 times to 11 languages.",
      "sourceUrl": "http://lyricstranslate.com/en/tamer-hosny-lyrics.html"
    },
    {
      "parentId": 3,
      "type": "text",
      "text": " including one which translates into \"God Bless You\" with these lyrics:"
    },
    {
      "type": "quote",
      "id": 4
    },
    {
      "type": "paragraph",
      "id": 5,
      "parentId": 4
    },
    {
      "parentId": 5,
      "type": "text",
      "text": "God protects you my love, my life, my precious/ and makes you live longer for me",
      "sourceTitle": "Translation of \"Allah Yebarekly Feek\" by Tamer Hosny from Arabic to English.",
      "sourceUrl": "http://lyricstranslate.com/en/Allah-Yebarekly-Feek-God-Bless-You.html"
    },
    {
      "type": "paragraph",
      "id": 6
    },
    {
      "parentId": 6,
      "type": "text",
      "text": "I also found a recording of him reciting or singing the adhan, or the Islamic call to prayer.",
      "sourceTitle": "Beautiful Adhaan (Islamic Call to Prayer) by Tamer Hosny.",
      "sourceUrl": "http://www.youtube.com/watch?v=yJ5eC2Xh5Og"
    },
    {
      "type": "paragraph",
      "id": 7
    },
    {
      "parentId": 7,
      "type": "text",
      "text": "Much of his religiously-themed music preaches tolerance and peace. In an English version of his song, \"Habibi Ya Rasoul Allah,\" he sings:"
    },
    {
      "type": "quote",
      "id": 8
    },
    {
      "type": "paragraph",
      "id": 9,
      "parentId": 8
    },
    {
      "parentId": 9,
      "type": "text",
      "text": "Messenger of love, messenger of peace, oh God's beloved. . . . You're the One who told us that this land needs peace.",
      "sourceTitle": "Tamer Hosny Habiby Ya Rasoul Allah English Version.",
      "sourceUrl": "http://www.youtube.com/watch?v=5VLsHZBp8a0"
    },
    {
      "type": "paragraph",
      "id": 10
    },
    {
      "parentId": 10,
      "type": "text",
      "text": "And many praised his song, \"Diny We Dinak,\" which condemned the bombing of a Christian church in Alexandria, Egypt in 2011, as a model of tolerance and understanding.",
      "sourceTitle": "I Hate Tamer Hosny, But Not This Song of His.",
      "sourceUrl": "http://hotarabicmusic.blogspot.com/2011/01/i-hate-tamer-hosny-but-not-this-song-of.html"
    },
    {
      "parentId": 10,
      "type": "text",
      "text": "\n"
    },
    {
      "type": "heading",
      "id": 11
    },
    {
      "parentId": 11,
      "type": "text",
      "text": "Political Lessons Learned"
    },
    {
      "type": "paragraph",
      "id": 12
    },
    {
      "parentId": 12,
      "type": "text",
      "text": "Hosny would probably have rather stayed out of politics. He's got his popular singing career, and it seems that would have been enough for him. But then this whole revolution thing happened. As a central component of the Arab Spring, protesters in 2011 successfully forced an end to the 30-year presidency of Hosni Mubarak."
    },
    {
      "type": "paragraph",
      "id": 13
    },
    {
      "parentId": 13,
      "type": "text",
      "text": "When the revolution began, the Mubarak government requested of Hosny that he speak to protesters and try to convince them to go home. When the singer complied, he was not well-received. (Some speculate that Hosny did the regime's bidding because he wanted to get on its good side after a draft-dodging scandal.)",
      "sourceTitle": "Why Tamer Hosny Won't Go Away.",
      "sourceUrl": "http://www.jadaliyya.com/pages/index/1290/"
    },
    {
      "type": "paragraph",
      "id": 14
    },
    {
      "parentId": 14,
      "type": "text",
      "text": "He tried to make up for it by going down to Tahrir Square to apologize and claim he was misled by the government, but protesters attacked him causing the military to intervene to protect the pop star.",
      "sourceTitle": "Tamer Hosny, Egypt's answer to Justin Timberlake, attacked by demonstrators in Cairo's Tahrir Square.",
      "sourceUrl": "http://www.nydailynews.com/news/world/tamer-hosny-egypt-answer-justin-timberlake-attacked-demonstrators-cairo-tahrir-square-article-1.135916"
    },
    {
      "parentId": 14,
      "type": "text",
      "text": " The "
    },
    {
      "parentId": 14,
      "type": "link",
      "text": "video",
      "sourceUrl": "http://www.youtube.com/watch?v=rxTiuuLlfmY"
    },
    {
      "parentId": 14,
      "type": "text",
      "text": " of him immediately afterward sobbing and saying he wanted to die didn't do much for his reputation, and prompted one demonstrator to tweet,"
    },
    {
      "type": "quote",
      "id": 15
    },
    {
      "type": "paragraph",
      "id": 16,
      "parentId": 15
    },
    {
      "parentId": 16,
      "type": "text",
      "text": "One of the great victories of the revolution is that it destroyed Tamer Hosny.",
      "sourceTitle": "Tamer Hosny, Egypt's answer to Justin Timberlake, attacked by demonstrators in Cairo's Tahrir Square.",
      "sourceUrl": "http://www.nydailynews.com/news/world/tamer-hosny-egypt-answer-justin-timberlake-attacked-demonstrators-cairo-tahrir-square-article-1.135916"
    },
    {
      "type": "paragraph",
      "id": 17
    },
    {
      "parentId": 17,
      "type": "text",
      "text": "He's done his best to convince Egyptians that he's on their side, even saying he'll release an album of songs for the revolution.",
      "sourceTitle": "Why Tamer Hosny Won't Go Away.",
      "sourceUrl": "http://www.jadaliyya.com/pages/index/1290/"
    },
    {
      "parentId": 17,
      "type": "text",
      "text": " But it looks like he learned his lesson. He refused to endorse a candidate in the 2012 presidential elections, the country's first democratic election, claiming he made a decision to stay non-political:"
    },
    {
      "type": "quote",
      "id": 18
    },
    {
      "type": "paragraph",
      "id": 19,
      "parentId": 18
    },
    {
      "parentId": 19,
      "type": "text",
      "text": "I had made a decision a while back to not discuss politics or reveal which presidential candidate I support. I did not reveal my choice in the first round of elections and do not intend on doing so in the second round.",
      "sourceTitle": "No politics for Tamer.",
      "sourceUrl": "http://www.albawaba.com/entertainment/tamer-hosny-haifa-wehbe-429416"
    },
    {
      "type": "paragraph",
      "id": 20
    },
    {
      "parentId": 20,
      "type": "text",
      "text": "Lesson learned. And his fans are probably thankful for it."
    }
  ],
  "wikipediaData": {
    "url": "https://en.wikipedia.org/wiki/Tamer_Hosny",
    "title": "Tamer Hosny",
    "image": {
      "name": "Ahwak_HQ_picture.jpg",
      "info": {
        "canonicaltitle": "File:Ahwak HQ picture.jpg",
        "thumburl": "https://upload.wikimedia.org/wikipedia/commons/thumb/0/00/Ahwak_HQ_picture.jpg/165px-Ahwak_HQ_picture.jpg",
        "thumbwidth": 165,
        "thumbheight": 300,
        "url": "https://upload.wikimedia.org/wikipedia/commons/0/00/Ahwak_HQ_picture.jpg",
        "descriptionurl": "https://commons.wikimedia.org/wiki/File:Ahwak_HQ_picture.jpg",
        "descriptionshorturl": "https://commons.wikimedia.org/w/index.php?curid=56591136",
        "extmetadata": {
          "DateTime": {
            "value": "2017-02-25 06:57:33",
            "source": "mediawiki-metadata",
            "hidden": ""
          },
          "ObjectName": {
            "value": "Ahwak HQ picture",
            "source": "mediawiki-metadata",
            "hidden": ""
          },
          "CommonsMetadataExtension": {
            "value": 1.2,
            "source": "extension",
            "hidden": ""
          },
          "Categories": {
            "value": "All media needing categories as of 2017|Media needing categories as of 25 February 2017|Self-published work",
            "source": "commons-categories",
            "hidden": ""
          },
          "Assessments": {
            "value": "",
            "source": "commons-categories",
            "hidden": ""
          },
          "ImageDescription": {
            "value": "tamer smiling",
            "source": "commons-desc-page"
          },
          "DateTimeOriginal": {
            "value": "2017-02-25",
            "source": "commons-desc-page"
          },
          "Credit": {
            "value": "<span class=\"int-own-work\" lang=\"en\">Own work</span>",
            "source": "commons-desc-page",
            "hidden": ""
          },
          "Artist": {
            "value": "<a href=\"//commons.wikimedia.org/w/index.php?title=User:Hishamal99&amp;action=edit&amp;redlink=1\" class=\"new\" title=\"User:Hishamal99 (page does not exist)\">Hishamal99</a>",
            "source": "commons-desc-page"
          },
          "LicenseShortName": {
            "value": "CC BY-SA 4.0",
            "source": "commons-desc-page",
            "hidden": ""
          },
          "UsageTerms": {
            "value": "Creative Commons Attribution-Share Alike 4.0",
            "source": "commons-desc-page",
            "hidden": ""
          },
          "AttributionRequired": {
            "value": "true",
            "source": "commons-desc-page",
            "hidden": ""
          },
          "LicenseUrl": {
            "value": "https://creativecommons.org/licenses/by-sa/4.0",
            "source": "commons-desc-page",
            "hidden": ""
          },
          "Copyrighted": {
            "value": "True",
            "source": "commons-desc-page",
            "hidden": ""
          },
          "Restrictions": {
            "value": "",
            "source": "commons-desc-page",
            "hidden": ""
          },
          "License": {
            "value": "cc-by-sa-4.0",
            "source": "commons-templates",
            "hidden": ""
          }
        }
      }
    },
    "isDisambiguation": false
  }
}