{
  "name": "Tim Allen",
  "relatedPeople": [
    {
      "slug": "steve-carell",
      "name": "Steve Carell"
    },
    {
      "slug": "hugh-laurie",
      "name": "Hugh Laurie"
    },
    {
      "slug": "rowan-atkinson",
      "name": "Rowan Atkinson"
    },
    {
      "slug": "robin-williams",
      "name": "Robin Williams"
    }
  ],
  "tags": [
    "actor",
    "comedian",
    "voice-actor",
    "white"
  ],
  "wikipediaData": {
    "url": "https://en.wikipedia.org/wiki/Tim_Allen",
    "title": "Tim Allen",
    "thumbnail": {
      "source": "https://upload.wikimedia.org/wikipedia/commons/thumb/f/ff/Tim_Allen_cropped.jpg/213px-Tim_Allen_cropped.jpg",
      "width": 213,
      "height": 300
    },
    "isDisambiguation": false
  }
}